{
  "facts": {
    "Discovered By": [
      {
        "text": "Scott S. Sheppard, David C. Jewitt and Jan T. Kleyna"
      }
    ],
    "Date of Discovery": [
      {
        "text": "6 March 2006"
      }
    ],
    "Orbit Size Around Saturn (semi-major axis)": [
      {
        "text": "22,920,400 km",
        "type": "Metric"
      },
      {
        "text": "14,242,076 miles",
        "type": "English"
      }
    ],
    "Periapsis (closest)": [
      {
        "text": "12,684,149 km",
        "type": "Metric"
      }
    ],
    "Apoapsis (farthest)": [
      {
        "text": "33,156,651 km",
        "type": "Metric"
      }
    ],
    "Sidereal Orbit Period (Length of Year)": [
      {
        "text": "3.549596167 Earth years "
      },
      {
        "text": "1,296.49 Earth days "
      },
      {
        "type": "comparison",
        "text": "Retrograde orbit"
      }
    ],
    "Orbit Circumference": [
      {
        "text": "136,538,557.68 km",
        "type": "Metric"
      }
    ],
    "Average Orbit Velocity": [
      {
        "text": "4,388.1 km/h",
        "type": "Metric"
      }
    ],
    "Orbit Eccentricity": [
      {
        "text": "0.4466"
      }
    ],
    "Orbit Inclination": [
      {
        "text": "169.141"
      },
      {
        "type": "comparison",
        "text": "Retrograde orbit"
      }
    ],
    "Mean Radius": [
      {
        "text": "3.0 (assuming an albedo of 0.04) km",
        "type": "Metric"
      },
      {
        "text": "1.9 miles",
        "type": "English"
      }
    ],
    "Equatorial Circumference": [
      {
        "text": "18.8 km",
        "type": "Metric"
      }
    ],
    "Volume": [
      {
        "text": "113 km3",
        "type": "Metric"
      }
    ],
    "Density": [
      {
        "text": "2.3 g/cm3",
        "type": "Metric"
      }
    ],
    "Surface Area": [
      {
        "text": "113.10 km2",
        "type": "Metric"
      }
    ]
  }
}
